emcommon/__init__.py
emcommon/common.py
emcommon/constellations.py
emcommon/items.py
emcommon/regions.py
emcommon/systems.py
emcommon/universe.py
emcommon-0.1.11.dist-info/LICENSE
emcommon-0.1.11.dist-info/METADATA
emcommon-0.1.11.dist-info/WHEEL
emcommon-0.1.11.dist-info/top_level.txt
emcommon-0.1.11.dist-info/RECORD
