Metadata-Version: 2.1
Name: emcommon
Version: 0.1.11
Summary: A collection of functions for common EM operations
Home-page: https://git.zswap.net/em/emcommon
Author: Nathan Spiegel
Author-email: nathan@zswap.net
Project-URL: Bug Tracker, https://git.zswap.net/em/emcommon/issues
Classifier: Programming Language :: Python :: 3
Classifier: License :: OSI Approved :: MIT License
Classifier: Operating System :: OS Independent
Requires-Python: >=3.5
License-File: LICENSE
Requires-Dist: requests
Requires-Dist: redis
Requires-Dist: future-fstrings
